onemapsg/__init__.py
onemapsg/onemap_client.py
onemapsg-1.0.3.dist-info/LICENSE
onemapsg-1.0.3.dist-info/METADATA
onemapsg-1.0.3.dist-info/WHEEL
onemapsg-1.0.3.dist-info/top_level.txt
onemapsg-1.0.3.dist-info/RECORD
