Metadata-Version: 2.1
Name: onemapsg
Version: 1.0.3
Summary: Python Wrapper Client for the OneMap API with automatic token handling
Home-page: https://github.com/methylDragon/one-map-api-client
Author: methylDragon
Author-email: methylDragon@gmail.com
License: MIT
Download-URL: https://pypi.org/project/onemapsg/
Keywords: onemap,api
Platform: UNKNOWN
